loko_extensions/__init__.py
loko_extensions/apps/__init__.py
loko_extensions/business/__init__.py
loko_extensions/business/decorator_fastapi.py
loko_extensions/business/decorators.py
loko_extensions/config/AppConfig.py
loko_extensions/config/__init__.py
loko_extensions/dao/__init__.py
loko_extensions/examples/__init__.py
loko_extensions/model/__init__.py
loko_extensions/model/components.py
loko_extensions/resources/__init__.py
loko_extensions/services/__init__.py
loko_extensions/services/services.py
loko_extensions/test/__init__.py
loko_extensions/utils/__init__.py
loko_extensions/utils/pathutils.py
loko_extensions-0.0.3.dist-info/METADATA
loko_extensions-0.0.3.dist-info/WHEEL
loko_extensions-0.0.3.dist-info/top_level.txt
loko_extensions-0.0.3.dist-info/RECORD
