Metadata-Version: 2.1
Name: loko-extensions
Version: 0.0.3
Summary: A framework for Loko extensions
Author: Live Tech
Author-email: f.dantonio@ilivetech.it
Classifier: Programming Language :: Python :: 3
Classifier: License :: OSI Approved :: MIT License
Classifier: Operating System :: OS Independent
Requires-Python: >3.5.0
Requires-Dist: loguru
